ckanext/__init__.py
ckanext/shopping_cart/__init__.py
ckanext/shopping_cart/cart.py
ckanext/shopping_cart/cli.py
ckanext/shopping_cart/helpers.py
ckanext/shopping_cart/plugin.py
ckanext/shopping_cart/views.py
ckanext/shopping_cart/assets/style.css
ckanext/shopping_cart/assets/webassets.yml
ckanext/shopping_cart/assets/js/shopping-cart-base.js
ckanext/shopping_cart/assets/js/shopping-cart-clear.js
ckanext/shopping_cart/assets/js/shopping-cart-dock.js
ckanext/shopping_cart/assets/js/shopping-cart-order.js
ckanext/shopping_cart/logic/__init__.py
ckanext/shopping_cart/logic/action.py
ckanext/shopping_cart/logic/auth.py
ckanext/shopping_cart/logic/schema.py
ckanext/shopping_cart/logic/validators.py
ckanext/shopping_cart/templates/ajax_snippets/shopping_cart_dock_empty.html
ckanext/shopping_cart/templates/ajax_snippets/shopping_cart_dock_footer.html
ckanext/shopping_cart/templates/ajax_snippets/shopping_cart_dock_heading.html
ckanext/shopping_cart/templates/ajax_snippets/shopping_cart_dock_not_empty.html
ckanext/shopping_cart/templates/shopping_cart/snippets/dock.html
ckanext/shopping_cart/tests/__init__.py
ckanext/shopping_cart/tests/conftest.py
ckanext/shopping_cart/tests/test_cart.py
ckanext/shopping_cart/tests/test_plugin.py
ckanext/shopping_cart/tests/logic/__init__.py
ckanext/shopping_cart/tests/logic/test_action.py
ckanext_shopping_cart-0.0.4.post1.dist-info/LICENSE
ckanext_shopping_cart-0.0.4.post1.dist-info/METADATA
ckanext_shopping_cart-0.0.4.post1.dist-info/WHEEL
ckanext_shopping_cart-0.0.4.post1.dist-info/entry_points.txt
ckanext_shopping_cart-0.0.4.post1.dist-info/top_level.txt
ckanext_shopping_cart-0.0.4.post1.dist-info/RECORD
